LICENSE
README.md
setup.py
natalify/__init__.py
natalify/__main__.py
natalify/natalify.py
natalify.egg-info/PKG-INFO
natalify.egg-info/SOURCES.txt
natalify.egg-info/dependency_links.txt
natalify.egg-info/requires.txt
natalify.egg-info/top_level.txt