Metadata-Version: 2.1
Name: natalify
Version: 3.4
Summary: A simple automation software for various tasks
Author: jack
Author-email: kinginjack@gmail.com
License: GPL-3.0
Platform: UNKNOWN
Classifier: License :: OSI Approved :: GNU General Public License v3 (GPLv3)
Classifier: Programming Language :: Python :: 3
Classifier: Programming Language :: Python :: 3.8
Classifier: Programming Language :: Python :: 3.9
Requires-Python: >=3.8
License-File: LICENSE
